py2json/__init__.py
py2json/ctor.py
py2json/encoders.py
py2json/fakit.py
py2json/obj2dict.py
py2json/util.py
py2json/w_glom.py
py2json/inspire/__init__.py
py2json/inspire/attribute_tree.py
py2json/inspire/example_fakit_use.py
py2json/inspire/func_serialization.py
py2json/inspire/serializing_sklearn_estimators.py
py2json-0.1.2.dist-info/LICENSE
py2json-0.1.2.dist-info/METADATA
py2json-0.1.2.dist-info/WHEEL
py2json-0.1.2.dist-info/top_level.txt
py2json-0.1.2.dist-info/RECORD
