Metadata-Version: 2.1
Name: py2json
Version: 0.1.2
Summary: Tools for json serialization of python objects
Home-page: UNKNOWN
License: mit
Platform: UNKNOWN
Requires-Dist: boltons
Requires-Dist: glom
Requires-Dist: numpy
Requires-Dist: i2
Requires-Dist: anytree
Requires-Dist: scikit-learn (==0.22.2)
